molconfviewer/__init__.py
molconfviewer/molconfviewer.py
molconfviewer-0.0.2.dist-info/LICENSE.txt
molconfviewer-0.0.2.dist-info/METADATA
molconfviewer-0.0.2.dist-info/WHEEL
molconfviewer-0.0.2.dist-info/top_level.txt
molconfviewer-0.0.2.dist-info/RECORD
