Metadata-Version: 2.1
Name: molconfviewer
Version: 0.0.2
Summary: Package to visualize molcules and their conformations in Jupyter
Home-page: http://pypi.python.org/pypi/molconfviewer/
Author: Benoit Baillif
Author-email: benoit.baillif@gmail.com
License: LICENSE.txt
Project-URL: Bug Tracker, https://github.com/pypa/sampleproject/issues
Platform: UNKNOWN
Classifier: Programming Language :: Python :: 3
Classifier: License :: OSI Approved :: MIT License
Classifier: Operating System :: OS Independent
License-File: LICENSE.txt
Requires-Dist: py3dmol
